Metadata-Version: 1.2
Name: cntn
Version: 0.0.3
Summary: Convert chinese written string to spoken string
Home-page: https://github.com/open-speech/cn-text-normalizer
Author: Meixu Song
Author-email: meixu.asr@gmail.com
License: MIT
Keywords: cntn
Platform: UNKNOWN
Requires-Python: >=3.3
